genepioneer/__init__.py
genepioneer/data_loader.py
genepioneer/evaluation.py
genepioneer/gene_analysis.py
genepioneer/network_analysis.py
genepioneer/network_builder.py
genepioneer/Data/evaluated_modules_result.json
genepioneer/Data/output.json
genepioneer/Data/benchmark-data/CGC.txt
genepioneer/Data/benchmark-data/CTAT.txt
genepioneer/Data/benchmark-data/HCD.txt
genepioneer/Data/benchmark-data/RULE.txt
genepioneer/Data/cancer-gene-data/Adrenal_network_features.csv
genepioneer/Data/cancer-gene-data/Bladder_network_features.csv
genepioneer/Data/cancer-gene-data/Brain_network_features.csv
genepioneer/Data/cancer-gene-data/Cervix_network_features.csv
genepioneer/Data/cancer-gene-data/Colon_network_features.csv
genepioneer/Data/cancer-gene-data/Corpus uteri_network_features.csv
genepioneer/Data/cancer-gene-data/Kidney_network_features.csv
genepioneer/Data/cancer-gene-data/Liver_network_features.csv
genepioneer/Data/cancer-gene-data/Ovary_network_features.csv
genepioneer/Data/cancer-gene-data/Prostate_network_features.csv
genepioneer/Data/cancer-gene-data/Skin_network_features.csv
genepioneer/Data/cancer-gene-data/Thyroid_network_features.csv
genepioneer/Data/module-data/Adrenal.json
genepioneer/Data/module-data/Bladder.json
genepioneer/Data/module-data/Brain.json
genepioneer/Data/module-data/Cervix.json
genepioneer/Data/module-data/Colon.json
genepioneer/Data/module-data/Corpus uteri.json
genepioneer/Data/module-data/Kidney.json
genepioneer/Data/module-data/Liver.json
genepioneer/Data/module-data/Ovary.json
genepioneer/Data/module-data/Prostate.json
genepioneer/Data/module-data/Skin.json
genepioneer/Data/module-data/Thyroid.json
tests/__init__.py
tests/test_data_loader.py
tests/test_evaluation.py
tests/test_gene_analysis.py
tests/test_network_analysis.py
tests/test_network_builder.py
genepioneer-1.1.0.dist-info/LICENSE
genepioneer-1.1.0.dist-info/METADATA
genepioneer-1.1.0.dist-info/WHEEL
genepioneer-1.1.0.dist-info/top_level.txt
genepioneer-1.1.0.dist-info/RECORD
