Metadata-Version: 2.2
Name: genepioneer
Version: 1.1.0
Summary: A Python package for identifying essential genes in cancer.
Home-page: https://github.com/amirhossein-haerian/GenePioneer
Author: Amirhossein Haerian, Golnaz Taheri
Author-email: haerian.amirhossein@gmail.com
License: MIT
Keywords: cancer,genomics,gene-analysis
Classifier: Development Status :: 3 - Alpha
Classifier: Intended Audience :: Science/Research
Classifier: Topic :: Scientific/Engineering :: Bio-Informatics
License-File: LICENSE
Requires-Dist: numpy
Requires-Dist: networkx
Requires-Dist: pandas
Requires-Dist: scipy
Requires-Dist: openpyxl
Requires-Dist: scipy
Requires-Dist: scikit-learn
Requires-Dist: igraph
Requires-Dist: leidenalg
Requires-Dist: matplotlib
Requires-Dist: gprofiler-official
Dynamic: author
Dynamic: author-email
Dynamic: classifier
Dynamic: description
Dynamic: description-content-type
Dynamic: home-page
Dynamic: keywords
Dynamic: license
Dynamic: requires-dist
Dynamic: summary
